ginniro/__init__.py
ginniro/dqn_imp.py
ginniro/dueling_imp.py
ginniro/base/__init__.py
ginniro/base/dqn_imp.py
ginniro/base/dueling_imp.py
ginniro/base/fpomdp_imp.py
ginniro/drawer/__init__.py
ginniro/drawer/drawer.py
ginniro/res/__init__.py
ginniro/res/add_imp.py
ginniro/res/mix_imp.py
ginniro/siamese/__init__.py
ginniro/siamese/dqn_imp.py
ginniro/siamese/mix_imp.py
ginniro/siamese/mul_imp.py
ginniro/siamese/siamese_imp.py
ginniro/split/__init__.py
ginniro/split/addshare_imp.py
ginniro/split/advmix_imp.py
ginniro/split/higher_imp.py
ginniro/split/mix_imp.py
ginniro/split/share_imp.py
ginniro/split/siamese_imp.py
ginniro/split/vote_imp.py
ginniro/target/__init__.py
ginniro/target/advmix_imp.py
ginniro/tripple/__init__.py
ginniro/tripple/add_imp.py
ginniro/tripple/mix_imp.py
ginniro/tripple/mul_imp.py
ginniro/util/__init__.py
ginniro/util/fetch_top.py
ginniro/worldmodel/__init__.py
ginniro/worldmodel/linear_emo_imp.py
ginniro/worldmodel/recurrent_emo_imp.py
ginniro/worldmodel/wo_feature_imp.py
GinniroDQN-0.9.0.dist-info/LICENSE
GinniroDQN-0.9.0.dist-info/METADATA
GinniroDQN-0.9.0.dist-info/WHEEL
GinniroDQN-0.9.0.dist-info/top_level.txt
GinniroDQN-0.9.0.dist-info/RECORD
